amazon_braket_sdk-1.111.0.dist-info/licenses/LICENSE
amazon_braket_sdk-1.111.0.dist-info/licenses/NOTICE
braket/ipython_utils.py
braket/_sdk/__init__.py
braket/_sdk/_version.py
braket/ahs/__init__.py
braket/ahs/analog_hamiltonian_simulation.py
braket/ahs/atom_arrangement.py
braket/ahs/canvas.py
braket/ahs/discretization_types.py
braket/ahs/driving_field.py
braket/ahs/field.py
braket/ahs/hamiltonian.py
braket/ahs/local_detuning.py
braket/ahs/pattern.py
braket/ahs/shifting_field.py
braket/annealing/__init__.py
braket/annealing/problem.py
braket/aws/__init__.py
braket/aws/aws_device.py
braket/aws/aws_quantum_job.py
braket/aws/aws_quantum_task.py
braket/aws/aws_quantum_task_batch.py
braket/aws/aws_session.py
braket/aws/direct_reservations.py
braket/aws/queue_information.py
braket/circuits/__init__.py
braket/circuits/angled_gate.py
braket/circuits/ascii_circuit_diagram.py
braket/circuits/basis_state.py
braket/circuits/braket_program_context.py
braket/circuits/circuit.py
braket/circuits/circuit_diagram.py
braket/circuits/circuit_helpers.py
braket/circuits/compiler_directive.py
braket/circuits/compiler_directives.py
braket/circuits/free_parameter.py
braket/circuits/free_parameter_expression.py
braket/circuits/gate.py
braket/circuits/gate_calibrations.py
braket/circuits/gates.py
braket/circuits/instruction.py
braket/circuits/measure.py
braket/circuits/moments.py
braket/circuits/noise.py
braket/circuits/noise_helpers.py
braket/circuits/noises.py
braket/circuits/observable.py
braket/circuits/observables.py
braket/circuits/operator.py
braket/circuits/parameterizable.py
braket/circuits/quantum_operator.py
braket/circuits/quantum_operator_helpers.py
braket/circuits/qubit.py
braket/circuits/qubit_set.py
braket/circuits/result_type.py
braket/circuits/result_types.py
braket/circuits/serialization.py
braket/circuits/translations.py
braket/circuits/unitary_calculation.py
braket/circuits/noise_model/__init__.py
braket/circuits/noise_model/circuit_instruction_criteria.py
braket/circuits/noise_model/criteria.py
braket/circuits/noise_model/criteria_input_parsing.py
amazon_braket_sdk-1.111.0.dist-info/METADATA
amazon_braket_sdk-1.111.0.dist-info/WHEEL
amazon_braket_sdk-1.111.0.dist-info/top_level.txt
amazon_braket_sdk-1.111.0.dist-info/RECORD
