Metadata-Version: 2.4
Name: amazon-braket-sdk
Version: 1.111.0
Summary: An open source library for interacting with quantum computing devices on Amazon Braket
Home-page: https://github.com/amazon-braket/amazon-braket-sdk-python
Author: Amazon Web Services
License: Apache License 2.0
Keywords: Amazon AWS Quantum
Classifier: Development Status :: 5 - Production/Stable
Classifier: Intended Audience :: Developers
Classifier: Intended Audience :: Education
Classifier: Intended Audience :: Science/Research
Classifier: Natural Language :: English
Classifier: License :: OSI Approved :: Apache Software License
Classifier: Programming Language :: Python
Classifier: Programming Language :: Python :: 3.11
Classifier: Programming Language :: Python :: 3.12
Classifier: Programming Language :: Python :: 3.13
Requires-Python: >= 3.11
License-File: LICENSE
License-File: NOTICE
Requires-Dist: amazon-braket-schemas>=1.27.0
Requires-Dist: amazon-braket-default-simulator>=1.32.0
Requires-Dist: oqpy~=0.3.7
Requires-Dist: backoff
Requires-Dist: boltons
Requires-Dist: boto3>=1.28.53
Requires-Dist: cloudpickle==2.2.1
Requires-Dist: nest-asyncio
Requires-Dist: networkx
Requires-Dist: numpy
Requires-Dist: openpulse
Requires-Dist: openqasm3
Requires-Dist: sympy
Requires-Dist: backports.entry-points-selectable
Provides-Extra: test
Requires-Dist: black; extra == "test"
Requires-Dist: botocore; extra == "test"
Requires-Dist: flake8; extra == "test"
Requires-Dist: isort; extra == "test"
Requires-Dist: jsonschema==3.2.0; extra == "test"
Requires-Dist: pre-commit; extra == "test"
Requires-Dist: pylint; extra == "test"
Requires-Dist: pytest; extra == "test"
Requires-Dist: pytest-cov; extra == "test"
Requires-Dist: pytest-rerunfailures<16.0; extra == "test"
Requires-Dist: pytest-xdist[psutil]; extra == "test"
Requires-Dist: tox; extra == "test"
Provides-Extra: docs
Requires-Dist: sphinx; extra == "docs"
Requires-Dist: sphinx-rtd-theme; extra == "docs"
Requires-Dist: sphinxcontrib-apidoc; extra == "docs"
Requires-Dist: sphinx-autodoc-typehints; extra == "docs"
Dynamic: author
Dynamic: classifier
Dynamic: description
Dynamic: description-content-type
Dynamic: home-page
Dynamic: keywords
Dynamic: license
Dynamic: license-file
Dynamic: provides-extra
Dynamic: requires-dist
Dynamic: requires-python
Dynamic: summary
